{ 
    "TC01": { "System_area": "Core",
              "Node_type": "CCDM",
              "Node" : "CCDM01",
              "GetDataFor": "NODE",
              "SubNetwork":"",
              "Data_source":"NetAn_ODBC",
              "Object_Aggregation": "Node",
              "Measure_type":"COUNTER,PDF_COUNTER,DYNCOUNTER,ERICSSON_KPI,RI",
              "Days" :"",
              "Time_selector" : "last30Days",
              "Aggregation" : "ROP",
              "Preceding_period" : "",
              "Preceding_period_unit" : "",
              "start_date" : "",
              "start_time" : "",
              "end_date" : "",
              "end_time" : "",
              "Time_selector2" : "",
              "Report_AccessType": "Public",
              "Check_Box" : "no",
              "Report_Description":  "desc",
              "Measure" : "TPS KPI for Ud Service-Service Provider",
              "SQL1" : "",
              "Data_Of_Col1" : "",
              "Data_Of_Col2" : "",
              "Formula" : ""
              },
	 "TC02": { "System_area": "Core",
              "Node_type": "CCDM",
              "Node" : "CCDM01",
              "GetDataFor": "NODE",
              "SubNetwork":"",
              "Data_source":"NetAn_ODBC",
              "Object_Aggregation": "Node",
              "Measure_type":"COUNTER,PDF_COUNTER,DYNCOUNTER,ERICSSON_KPI,RI",
              "Days" :"",
              "Time_selector" : "createInterval",
              "Aggregation" : "Hour",
              "Time_selector2" : "selectedInterval",
              "Preceding_period" : "",
              "Preceding_period_unit" : "",
              "start_date" : "28/08/2022",
              "start_time" : "",
              "end_date" : "06/09/2022",
              "end_time" : "",
              "Report_AccessType": "Public",
              "Check_Box" : "no",
              "Report_Description":  "desc",
              "Measure" : "TPS KPI for Ud Service-Service Provider",
              "SQL1" : "",
              "Data_Of_Col1" : "",
              "Data_Of_Col2" : "",
              "Formula" : ""
              } ,
       "TC03": { "System_area": "Core",
              "Node_type": "CCDM",
              "Node" : "CCDM01",
              "GetDataFor": "NODE",
              "SubNetwork":"",
              "Data_source":"NetAn_ODBC",
              "Object_Aggregation": "Node",
              "Measure_type":"Counter",
              "Days" :"",
              "Time_selector" : "last30Days",
              "Aggregation" : "Day",
              "Time_selector2" : "",
              "Preceding_period" : "",
              "Preceding_period_unit" : "",
              "start_date" : "",
              "start_time" : "",
              "end_date" : "",
              "end_time" : "",
              "Report_AccessType": "Public",
              "Check_Box" : "yes",
              "Report_Description":  "testReport",
              "Measure" : "TPS KPI for Ud Service-Service Provider",
              "SQL1" : "",
              "Data_Of_Col1" : "",
              "Data_Of_Col2" : "",
              "Formula" : ""
              } ,
		"TC04": { "System_area": "Core",
              "Node_type": "CCDM",
              "Node" : "CCDM01",
              "GetDataFor": "NODE",
              "Data_source":"NetAn_ODBC",
              "SubNetwork":"",
              "Object_Aggregation": "All Selected",
              "Measure_type":"Counter",
              "Days" :"",
              "Time_selector" : "calendarInterval",
              "Aggregation" : "Day",
              "Time_selector2" : "",
              "Preceding_period" : "",
              "Preceding_period_unit" : "",
              "start_date" : "01/09/2022",
              "start_time" : "",
              "end_date" : "09/09/2022",
              "end_time" : "",
              "Report_AccessType": "Public",
              "Check_Box" : "no",
              "Report_Description":  "testReport",
              "Measure" : "ERIC_ACT_MAPI_REQUESTS_RECV.DC_E_CCDM_ACT_MAPI_RAW",
              "SQL1" : "select \\"ReportName\\" FROM \\"tblSavedReports\\" WHERE \\"ReportName\\" =REPORT_NAME",
              "Data_Of_Col1" : "",
              "Data_Of_Col2" : "",
              "Formula" : ""
              }  ,
          "TC05": { "System_area": "Radio",
              "Node_type": "NR",
              "Node" : "G2RBS_01",
              "GetDataFor": "NODE",
              "SubNetwork":"",
              "Data_source":"NetAn_ODBC",
              "Object_Aggregation": "Node",
              "Measure_type":"Counter",
              "Days" :"",
              "Time_selector" : "last7Days",
              "Aggregation" : "ROP",
              "Time_selector2" : "",
              "Preceding_period" : "",
              "Preceding_period_unit" : "",
              "start_date" : "",
              "start_time" : "",
              "end_date" : "",
              "end_time" : "",
              "Report_AccessType": "Public",
              "Check_Box" : "no",
              "Report_Description":  "test report",
              "Measure" : "PMRADIORACBFAILMSG1OOC.DC_E_NR_BEAM_RAW",
              "SQL1" : "select \\"ReportName\\" FROM \\"tblSavedReports\\" WHERE \\"ReportName\\" =REPORT_NAME",
              "Data_Of_Col1" : "",
              "Data_Of_Col2" : "",
              "Formula" : ""
              }   ,
       "TC06": { "System_area": "Core",
              "Node_type": "CCDM",
              "Node" : "CCDM01",
              "GetDataFor": "NODE",
              "SubNetwork":"",
              "Data_source":"NetAn_ODBC",
              "Object_Aggregation": "No Aggregation",
              "Measure_type":"Counter",
              "Days" :"",
              "Time_selector" : "last7Days",
              "Aggregation" : "ROP",
              "Time_selector2" : "",
              "Preceding_period" : "",
              "Preceding_period_unit" : "",
              "start_date" : "01/09/2022",
              "start_time" : "",
              "end_date" : "09/09/2022",
              "end_time" : "",
              "Report_AccessType": "Public",
              "Check_Box" : "no",
              "Report_Description":  "testReport",
              "Measure" : "ERIC_ACT_MAPI_REQUESTS_RECV.DC_E_CCDM_ACT_MAPI_RAW",
              "SQL1" : "select \\"ReportName\\" FROM \\"tblSavedReports\\" WHERE \\"ReportName\\" =REPORT_NAME",
              "Data_Of_Col1" : "",
              "Data_Of_Col2" : "",
              "Formula" : ""
              }   ,
          "TC07": { "System_area": "Radio",
              "Node_type": "NR",
              "Node" : "",
              "GetDataFor": "NETWORK",
              "SubNetwork":"",
              "Data_source":"NetAn_ODBC",
              "Object_Aggregation": "Cell",
              "Measure_type":"Counter",
              "Days" :"",
              "Time_selector" : "calendarInterval",
              "Aggregation" : "Day",
              "Time_selector2" : "",
              "Preceding_period" : "",
              "Preceding_period_unit" : "",
              "start_date" : "",
              "start_time" : "",
              "end_date" : "",
              "end_time" : "",
              "Report_AccessType": "Public",
              "Check_Box" : "no",
              "Report_Description":  "testReport",
              "Measure" : "PMRADIORACBFAILMSG1OOC.DC_E_NR_BEAM_RAW",
              "SQL1" : "select \\"ReportName\\" FROM \\"tblSavedReports\\" WHERE \\"ReportName\\" =REPORT_NAME",
              "Data_Of_Col1" : "",
              "Data_Of_Col2" : "",
              "Formula" : ""
              }   ,
      "TC08": { "System_area": "Radio",
              "Node_type": "NR",
              "Node" : "",
              "GetDataFor": "SUBNETWORK",
              "SubNetwork": "5G",
              "Data_source":"NetAn_ODBC",
              "Object_Aggregation": "No Aggregation",
              "Measure_type":"Counter",
              "Days" :"",
              "Time_selector" : "last7Days",
              "Aggregation" : "ROP",
              "Time_selector2" : "",
              "Preceding_period" : "",
              "Preceding_period_unit" : "",
              "start_date" : "",
              "start_time" : "",
              "end_date" : "",
              "end_time" : "",
              "Report_AccessType": "Public",
              "Check_Box" : "no",
              "Report_Description":  "testReport",
              "Measure" : "PMRADIORACBFAILMSG1OOC.DC_E_NR_BEAM_RAW",
              "SQL1" : "select \\"ReportName\\" FROM \\"tblSavedReports\\" WHERE \\"ReportName\\" =REPORT_NAME",
              "Data_Of_Col1" : "",
              "Data_Of_Col2" : "",
              "Formula" : ""
              }   ,
      "TC09": { "System_area": "Radio",
              "Node_type": "NR",
              "Node" : "",
              "GetDataFor": "NETWORK",
              "SubNetwork": "",
              "Data_source":"NetAn_ODBC",
              "Object_Aggregation": "No Aggregation",
              "Measure_type":"Counter",
              "Days" :"",
              "Time_selector" : "last7Days",
              "Aggregation" : "ROP",
              "Time_selector2" : "",
              "Preceding_period" : "",
              "Preceding_period_unit" : "",
              "start_date" : "",
              "start_time" : "",
              "end_date" : "",
              "end_time" : "",
              "Report_AccessType": "Public",
              "Check_Box" : "no",
              "Report_Description":  "testReport",
              "Measure" : "PMRADIORACBFAILMSG1OOC.DC_E_NR_BEAM_RAW",
              "SQL1" : "select \\"ReportName\\" FROM \\"tblSavedReports\\" WHERE \\"ReportName\\" =REPORT_NAME",
              "Data_Of_Col1" : "",
              "Data_Of_Col2" : "",
              "Formula" : ""
              }   ,
          "TC10": { "System_area": "Core",
              "Node_type": "CCDM",
              "Node" : "CCDM01",
              "GetDataFor": "NODE",
              "SubNetwork": "",
              "Data_source":"NetAn_ODBC",
              "Object_Aggregation": "No Aggregation",
              "Measure_type":"Counter",
              "Days" :"",
              "Time_selector" : "last30Days",
              "Aggregation" : "Day",
              "Time_selector2" : "",
              "Preceding_period" : "",
              "Preceding_period_unit" : "",
              "start_date" : "",
              "start_time" : "",
              "end_date" : "",
              "end_time" : "",
              "Report_AccessType": "Public",
              "Check_Box" : "no",
              "Report_Description":  "testReport",
              "Measure" : "ERIC_ACT_MAPI_REQUESTS_RECV.DC_E_CCDM_ACT_MAPI_RAW",
              "SQL1" : "select \\"ReportName\\" FROM \\"tblSavedReports\\" WHERE \\"ReportName\\" =REPORT_NAME",
              "Data_Of_Col1" : "",
              "Data_Of_Col2" : "",
              "Formula" : ""
              } ,
       "TC11": { "CollectionName" : "Collection_Static",
              "ENIQ_data_source" : "NetAn_ODBC",
    		  "Single_node_or_collection" : "Collection",
              "System_area": "Core",
              "Node_type": "CCDM",
              "Node" : "CCDM01",
              "Wild_card" : "",
              "GetDataFor": "COLLECTION",
              "SubNetwork": "",
              "Data_source":"NetAn_ODBC",
              "Object_Aggregation": "No Aggregation",
              "Measure_type":"Counter",
              "Days" :"",
              "Time_selector" : "last30Days",
              "Aggregation" : "Day",
              "Time_selector2" : "",
              "Preceding_period" : "",
              "Preceding_period_unit" : "",
              "start_date" : "",
              "start_time" : "",
              "end_date" : "",
              "end_time" : "",
              "Report_AccessType": "Public",
              "Check_Box" : "no",
              "Report_Description":  "testReport",
              "Measure" : "ERIC_ACT_MAPI_REQUESTS_RECV.DC_E_CCDM_ACT_MAPI_RAW",
              "SQL1" : "select \\"ReportName\\" FROM \\"tblSavedReports\\" WHERE \\"ReportName\\" =REPORT_NAME",
              "Data_Of_Col1" : "",
              "Data_Of_Col2" : "",
              "Formula" : ""
              } ,
      "TC12": { "System_area": "Core",
              "Node_type": "CCDM",
              "Node" : "CCDM01",
              "GetDataFor": "NODE",
              "SubNetwork": "",
              "Data_source":"NetAn_ODBC",
              "Object_Aggregation": "No Aggregation",
              "Measure_type":"Counter",
              "Days" :"",
              "Time_selector" : "createInterval",
              "Aggregation" : "ROP",
              "Time_selector2" : "selectedInterval",
              "Preceding_period" : "",
              "Preceding_period_unit" : "",
              "start_date" : "28/08/2022",
              "start_time" : "",
              "end_date" : "06/09/2022",
              "end_time" : "",
              "Report_AccessType": "Public",
              "Check_Box" : "no",
              "Report_Description":  "testReport",
              "Measure" : "ERIC_ACT_MAPI_REQUESTS_RECV.DC_E_CCDM_ACT_MAPI_RAW",
              "SQL1" : "select \\"ReportName\\" FROM \\"tblSavedReports\\" WHERE \\"ReportName\\" =REPORT_NAME",
              "Data_Of_Col1" : "",
              "Data_Of_Col2" : "",
              "Formula" : ""
              }      ,
       "TC13": { "System_area": "Radio",
              "Node_type": "NR",
              "Node" : "G2RBS_01",
              "GetDataFor": "NODE",
              "SubNetwork":"",
              "Days" : "\\"Monday\\",\\"Tuesday\\"",
              "Data_source":"NetAn_ODBC",
              "Object_Aggregation": "No Aggregation",
              "Measure_type":"Counter",
              "Time_selector" : "precedingPeriod",
              "Aggregation" : "Day",
              "Time_selector2" : "",
              "Preceding_period" : "",
              "Preceding_period_unit" : "",
              "start_date" : "",
              "start_time" : "",
              "end_date" : "",
              "end_time" : "",
              "Report_AccessType": "Public",
              "Check_Box" : "no",
              "Report_Description":  "testReport",
              "Measure" : "PMRADIORACBFAILMSG1OOC.DC_E_NR_BEAM_RAW",
              "SQL1" : "select \\"ReportName\\" FROM \\"tblSavedReports\\" WHERE \\"ReportName\\" =REPORT_NAME",
              "Data_Of_Col1" : "",
              "Data_Of_Col2" : "",
              "Formula" : ""
              },
		"TC14": { "System_area": "Core",
              "Node_type": "CCDM",
              "Node" : "CCDM01",
              "GetDataFor": "NODE",
              "Data_source":"NetAn_ODBC",
              "SubNetwork":"",
              "Object_Aggregation": "No Aggregation",
              "Measure_type":"Counter",
              "Days" :"",
              "Time_selector" : "calendarInterval",
              "Aggregation" : "Day",
              "Time_selector2" : "",
              "Preceding_period" : "",
              "Preceding_period_unit" : "",
              "start_date" : "27/08/2022",
              "start_time" : "01:00",
              "end_date" : "07/09/2022",
              "end_time" : "23:00",
              "Report_AccessType": "Public",
              "Check_Box" : "no",
              "Report_Description":  "testGraph",
              "Measure" : "ERIC_ACT_MAPI_REQUESTS_RECV.DC_E_CCDM_ACT_MAPI_RAW",
              "SQL1" : "select \\"ReportName\\" FROM \\"tblSavedReports\\" WHERE \\"ReportName\\" =REPORT_NAME",
              "Data_Of_Col1" : "",
              "Data_Of_Col2" : "",
              "Formula" : ""
              }   ,
      "TC15": { "System_area": "Core",
              "Node_type": "CCDM",
              "Node" : "CCDM01",
              "GetDataFor": "NODE",
              "SubNetwork": "",
              "Data_source":"NetAn_ODBC",
              "Object_Aggregation": "No Aggregation",
              "Measure_type":"Counter",
              "Days" :"",
              "Time_selector" : "createInterval",
              "Aggregation" : "Month",
              "Time_selector2" : "selectedInterval",
              "Preceding_period" : "",
              "Preceding_period_unit" : "",
              "start_date" : "28/09/2022",
              "start_time" : "",
              "end_date" : "06/10/2022",
              "end_time" : "",
              "Report_AccessType": "Public",
              "Check_Box" : "no",
              "Report_Description":  "ExtIntervalMonth",
              "Measure" : "ERIC_ACT_MAPI_REQUESTS_RECV.DC_E_CCDM_ACT_MAPI_RAW",
              "SQL1" : "select \\"ReportName\\" FROM \\"tblSavedReports\\" WHERE \\"ReportName\\" =REPORT_NAME",
              "Data_Of_Col1" : "",
              "Data_Of_Col2" : "",
              "Formula" : ""
              }    ,
      "TC16": { "System_area": "Core",
              "Node_type": "CCDM",
              "Node" : "CCDM01",
              "GetDataFor": "NODE",
              "SubNetwork": "",
              "Data_source":"NetAn_ODBC",
              "Object_Aggregation": "No Aggregation",
              "Measure_type":"Counter",
              "Days" :"",
              "Time_selector" : "calendarInterval",
              "Aggregation" : "Month",
              "Time_selector2" : "",
              "Preceding_period" : "",
              "Preceding_period_unit" : "",
              "start_date" : "28/09/2022",
              "start_time" : "06:00",
              "end_date" : "06/10/2022",
              "end_time" : "12:00",
              "Report_AccessType": "Public",
              "Check_Box" : "no",
              "Report_Description":  "CalendarIntervalMonth",
              "Measure" : "ERIC_ACT_MAPI_REQUESTS_RECV.DC_E_CCDM_ACT_MAPI_RAW",
              "SQL1" : "select \\"ReportName\\" FROM \\"tblSavedReports\\" WHERE \\"ReportName\\" =REPORT_NAME",
              "Data_Of_Col1" : "",
              "Data_Of_Col2" : "",
              "Formula" : ""
              }   ,
      "TC17": { "System_area": "Core",
              "Node_type": "CCDM",
              "Node" : "CCDM01",
              "GetDataFor": "NODE",
              "SubNetwork": "",
              "Data_source":"NetAn_ODBC",
              "Object_Aggregation": "No Aggregation",
              "Measure_type":"Counter",
              "Days" :"",
              "Time_selector" : "calendarInterval",
              "Aggregation" : "Month",
              "Time_selector2" : "",
              "Preceding_period" : "",
              "Preceding_period_unit" : "",
              "start_date" : "28/09/2022",
              "start_time" : "06:00",
              "end_date" : "06/10/2022",
              "end_time" : "12:00",
              "Report_AccessType": "Public",
              "Check_Box" : "no",
              "Report_Description":  "CalendarIntervalMonth",
              "Measure" : "ERIC_ACT_MAPI_REQUESTS_RECV.DC_E_CCDM_ACT_MAPI_RAW",
              "SQL1" : "select \\"ReportName\\" FROM \\"tblSavedReports\\" WHERE \\"ReportName\\" =REPORT_NAME",
              "Data_Of_Col1" : "",
              "Data_Of_Col2" : "",
              "Formula" : ""
              }   ,
       "TC18": { "System_area": "Core",
              "Node_type": "CCDM",
              "Node" : "CCDM01",
              "GetDataFor": "NODE",
              "SubNetwork": "",
              "Data_source":"NetAn_ODBC",
              "Object_Aggregation": "No Aggregation",
              "Measure_type":"Counter",
              "Days" :"",
              "Time_selector" : "createInterval",
              "Aggregation" : "Month",
              "Time_selector2" : "selectedInterval",
              "Preceding_period" : "",
              "Preceding_period_unit" : "",
              "start_date" : "29/09/2022",
              "start_time" : "06:00",
              "end_date" : "06/10/2022",
              "end_time" : "12:00",
              "Report_AccessType": "Public",
              "Check_Box" : "yes",
              "Report_Description":  "CalendarMonthAndIntegrity",
              "Measure" : "ERIC_ACT_MAPI_REQUESTS_RECV.DC_E_CCDM_ACT_MAPI_RAW",
              "SQL1" : "select \\"ReportName\\" FROM \\"tblSavedReports\\" WHERE \\"ReportName\\" =REPORT_NAME",
              "Data_Of_Col1" : "",
              "Data_Of_Col2" : "",
              "Formula" : ""
              }  ,
       "TC19": { "System_area": "Core",
              "Node_type": "CCDM",
              "Node" : "CCDM01",
              "GetDataFor": "NODE",
              "SubNetwork": "",
              "Data_source":"NetAn_ODBC",
              "Object_Aggregation": "No Aggregation",
              "Measure_type":"Counter",
              "Days" :"",
              "Time_selector" : "createInterval",
              "Aggregation" : "Month",
              "Time_selector2" : "selectedInterval",
              "Preceding_period" : "",
              "Preceding_period_unit" : "",
              "start_date" : "29/09/2022",
              "start_time" : "06:00",
              "end_date" : "06/10/2022",
              "end_time" : "12:00",
              "Report_AccessType": "Public",
              "Check_Box" : "yes",
              "Report_Description":  "MonthIDValidate",
              "Measure" : "ERIC_ACT_MAPI_REQUESTS_RECV.DC_E_CCDM_ACT_MAPI_RAW",
              "SQL1" : "select \\"ReportName\\" FROM \\"tblSavedReports\\" WHERE \\"ReportName\\" =REPORT_NAME",
              "Data_Of_Col1" : "",
              "Data_Of_Col2" : "",
              "Formula" : ""
              } ,
      "TC20": { "System_area": "Core",
              "Node_type": "CCDM",
              "Node" : "CCDM01",
              "GetDataFor": "NODE",
              "SubNetwork": "",
              "Data_source":"NetAn_ODBC",
              "Object_Aggregation": "No Aggregation",
              "Measure_type":"Counter",
              "Days" :"",
              "Time_selector" : "calendarInterval",
              "Aggregation" : "Month",
              "Time_selector2" : "",
              "Preceding_period" : "",
              "Preceding_period_unit" : "",
              "start_date" : "28/09/2022",
              "start_time" : "06:00",
              "end_date" : "06/10/2022",
              "end_time" : "12:00",
              "Report_AccessType": "Public",
              "Check_Box" : "no",
              "Report_Description":  "EditReportMonthAgg",
              "Measure" : "ERIC_ACT_MAPI_REQUESTS_RECV.DC_E_CCDM_ACT_MAPI_RAW",
              "SQL1" : "select \\"ReportName\\" FROM \\"tblSavedReports\\" WHERE \\"ReportName\\" =REPORT_NAME",
              "Data_Of_Col1" : "",
              "Data_Of_Col2" : "",
              "Formula" : ""
              }
              
      
}