{ 
    "TC01": { 
    		  "System_area": "Radio",
              "Node_type": "ERBS",
              "Data_source":"NetAn_ODBC",
              "Get_Data_for":"Node(s)",
              "Aggregation":"No Aggregation",
			  "Node" : "ERBS1",
              "Measure_type":"COUNTER",
              "Measure":" BFDSESSDOWNCOUNT.DC_E_TCU_BFDSESSIONIPV6_RAW",
              "Time_selector" : "Preceding Period",
              "Aggregation_in_select_time" : "Day",
              "Preceding_period" : "2",
              "Preceding_period_units" : "Day(s)",
              "Time_title_validation" : "Day",
              "get_data_for_Columns":"",
              "Columns_displayed":"",
              "Report_name":"",
              "Report_AccessType": "",
              "Report_Description":"",
              "Formula" : ""
            },
    "TC02": { 
    		  "System_area": "Radio",
              "Node_type": "ERBS",
              "Data_source":"NetAn_ODBC",
              "Get_Data_for":"Node(s)",
              "Aggregation":"No Aggregation",
			  "Node" : "ERBS1",
              "Measure_type":"COUNTER",
              "Measure":"DHCPV6INSERVERMSGSHC.DC_E_TCU_DHCPRELAYIPV6_RAW",
              "Time_selector" : "Preceding Period",
              "Aggregation_in_select_time" : "Hour",
              "Preceding_period" : "2",
              "Preceding_period_units" : "Day(s)",
              "Time_title_validation" : "Hour",
              "get_data_for_Columns":"",
              "Columns_displayed":"",
              "Report_name":"",
              "Report_AccessType": "",
              "Report_Description":"",
              "Formula" : ""
            },
	"TC03": { 
    		  "System_area": "Radio",
              "Node_type": "ERBS",
              "Data_source":"NetAn_ODBC",
              "Get_Data_for":"Node(s)",
              "Aggregation":"No Aggregation",
			  "Node" : "ERBS1",
              "Measure_type":"COUNTER",
              "Measure":"DHCPV6INSERVERMSGSHC.DC_E_TCU_DHCPRELAYIPV6_RAW",
              "Time_selector" : "Preceding Period",
              "Aggregation_in_select_time" : "Month",
              "Preceding_period" : "2",
              "Preceding_period_units" : "Month(s)",
              "Time_title_validation" : "Month",
              "get_data_for_Columns":"",
              "Columns_displayed":"",
              "Report_name":"",
              "Report_AccessType": "",
              "Report_Description":"",
              "Formula" : ""
            },
	"TC04": { 
    		  "System_area": "Radio",
              "Node_type": "ERBS",
              "Data_source":"NetAn_ODBC",
              "Get_Data_for":"Node(s)",
              "Aggregation":"No Aggregation",
			  "Node" : "ERBS1",
              "Measure_type":"COUNTER",
              "Measure":"DHCPV6INSERVERMSGSHC.DC_E_TCU_DHCPRELAYIPV6_RAW",
              "Time_selector" : "Preceding Period",
              "Aggregation_in_select_time" : "ROP",
              "Preceding_period" : "2",
              "Preceding_period_units" : "Day(s)",
              "Time_title_validation" : "ROP",
              "get_data_for_Columns":"",
              "Columns_displayed":"",
              "Report_name":"",
              "Report_AccessType": "",
              "Report_Description":"",
              "Formula" : ""
            },
	"TC05": { 
    		  "System_area": "Radio",
              "Node_type": "NR",
              "Data_source":"NetAn_ODBC",
              "Get_Data_for":"Node(s)",
              "Aggregation":"No Aggregation",
			  "Node" : "G2RBS01",
              "Measure_type":"PDF_COUNTER",
              "Measure":"PMCACONFIGDLSUMENDCDISTR.DC_E_NR_NRCELLCU_V_RAW",
              "Time_selector" : "Preceding Period",
              "Aggregation_in_select_time" : "Week",
              "Preceding_period" : "2",
              "Preceding_period_units" : "Month(s)",
              "Time_title_validation" : "Week",
              "get_data_for_Columns":"",
              "Columns_displayed":"",
              "Report_name":"",
              "Report_AccessType": "",
              "Report_Description":"",
              "Formula" : ""
            },
	"TC06": { 
    		  "System_area": "Radio",
              "Node_type": "NR",
              "Data_source":"NetAn_ODBC",
              "Get_Data_for":"Node(s)",
              "Aggregation":"No Aggregation",
			        "Node" : "G2RBS01",
              "Measure_type":"PDF_COUNTER",
              "Measure":"PMCACONFIGDLSUMENDCDISTR.DC_E_NR_NRCELLCU_V_RAW",
              "Time_selector" : "Preceding Period",
              "Aggregation_in_select_time" : "BusyHour",
              "Preceding_period" : "2",
              "Preceding_period_units" : "Day(s)",
              "Time_title_validation" : "DAYBH",
              "get_data_for_Columns":"",
              "Columns_displayed":"",
              "Report_name":"",
              "Report_AccessType": "",
              "Report_Description":"",
              "Formula" : ""
            }
}