<Ptexport version="1.3.0">
<Response>
<RR cid="1296003098" sid="98" eod="0">
<RR1 direction="0" statStatus="5" syncStatus="90" statTime="1700390700000" intervalms="900000" duplicatepkts="5" dmin="55" dmean="74" dvpMi="5" dvp95="99" lostperiods="68" jmin="76" dpMi="4" dvmean="87" lostperc="56" lostburstmax="92" jmax="22" dStdDev="65" lostpkts="69" dvpHi="42" dp25="77" toolatepkts="57" lostburstmin="38" dvpLo="62" vpriomin="67" dp95="39" dvmax="7" jmean="53" tosmin="88" jpMi="76" jpLo="45" ttlmin="97" dvp50="56" rxbytes="36" misorderpkts="41" jStdDev="56" jp25="76" jpHi="90" vpriomax="92" dpLo="24" mos="90" ttlmax="69" jp95="48" dvp75="30" jp50="47" dp50="61" jp75="90" rxpkts="74" dvp25="12" dpHi="61" dmax="10" dp75="38" tosmax="55" cksum="21" statRound="31" firstpktOffset="47" lastpktOffset="57" firstpktSeq="15" lastpktSeq="77" />
<RR1 direction="1" statStatus="15" syncStatus="59" statTime="1700390700000" intervalms="900000" duplicatepkts="64" dmin="61" dmean="21" dvpMi="55" dvp95="33" lostperiods="20" jmin="71" dpMi="1" dvmean="6" lostperc="25" lostburstmax="61" jmax="92" dStdDev="77" lostpkts="12" dvpHi="78" dp25="59" toolatepkts="8" lostburstmin="68" dvpLo="50" vpriomin="62" dp95="6" dvmax="87" jmean="70" tosmin="82" jpMi="25" jpLo="23" ttlmin="33" dvp50="59" rxbytes="51" misorderpkts="66" jStdDev="77" jp25="6" jpHi="13" vpriomax="30" dpLo="60" mos="77" ttlmax="97" jp95="57" dvp75="66" jp50="95" dp50="44" jp75="46" rxpkts="65" dvp25="34" dpHi="86" dmax="57" dp75="65" tosmax="78" cksum="82" statRound="63" firstpktOffset="23" lastpktOffset="43" firstpktSeq="65" lastpktSeq="29" />
</RR>
<RR cid="1296003099" sid="99" eod="0">
<RR1 direction="0" statStatus="91" syncStatus="63" statTime="1700390700000" intervalms="900000" duplicatepkts="11" dmin="25" dmean="53" dvpMi="73" dvp95="37" lostperiods="11" jmin="13" dpMi="42" dvmean="57" lostperc="20" lostburstmax="76" jmax="86" dStdDev="95" lostpkts="99" dvpHi="8" dp25="38" toolatepkts="15" lostburstmin="2" dvpLo="51" vpriomin="55" dp95="45" dvmax="3" jmean="5" tosmin="42" jpMi="66" jpLo="31" ttlmin="26" dvp50="73" rxbytes="46" misorderpkts="64" jStdDev="27" jp25="45" jpHi="84" vpriomax="77" dpLo="97" mos="29" ttlmax="20" jp95="94" dvp75="53" jp50="67" dp50="22" jp75="4" rxpkts="53" dvp25="9" dpHi="22" dmax="55" dp75="85" tosmax="30" cksum="57" statRound="26" firstpktOffset="47" lastpktOffset="25" firstpktSeq="58" lastpktSeq="14" />
<RR1 direction="1" statStatus="84" syncStatus="40" statTime="1700390700000" intervalms="900000" duplicatepkts="27" dmin="25" dmean="36" dvpMi="22" dvp95="1" lostperiods="25" jmin="2" dpMi="56" dvmean="79" lostperc="48" lostburstmax="61" jmax="73" dStdDev="43" lostpkts="27" dvpHi="43" dp25="80" toolatepkts="28" lostburstmin="25" dvpLo="70" vpriomin="86" dp95="75" dvmax="62" jmean="99" tosmin="92" jpMi="78" jpLo="98" ttlmin="7" dvp50="87" rxbytes="95" misorderpkts="50" jStdDev="77" jp25="93" jpHi="74" vpriomax="34" dpLo="11" mos="26" ttlmax="67" jp95="73" dvp75="98" jp50="63" dp50="66" jp75="49" rxpkts="13" dvp25="59" dpHi="6" dmax="59" dp75="27" tosmax="27" cksum="24" statRound="5" firstpktOffset="7" lastpktOffset="62" firstpktSeq="47" lastpktSeq="72" />
</RR>
</Response>
</Ptexport>
