<Ptexport version="1.3.0">
<Response>
<RR cid="1296003532" sid="532" eod="0">
<RR1 direction="0" statStatus="41" syncStatus="10" statTime="1700390700000" intervalms="900000" duplicatepkts="13" dmin="99" dmean="13" dvpMi="12" dvp95="7" lostperiods="62" jmin="23" dpMi="67" dvmean="8" lostperc="37" lostburstmax="60" jmax="3" dStdDev="55" lostpkts="57" dvpHi="82" dp25="83" toolatepkts="67" lostburstmin="35" dvpLo="74" vpriomin="51" dp95="9" dvmax="93" jmean="46" tosmin="70" jpMi="81" jpLo="36" ttlmin="63" dvp50="62" rxbytes="75" misorderpkts="24" jStdDev="89" jp25="29" jpHi="64" vpriomax="31" dpLo="72" mos="47" ttlmax="35" jp95="56" dvp75="73" jp50="73" dp50="40" jp75="91" rxpkts="36" dvp25="92" dpHi="96" dmax="67" dp75="88" tosmax="88" cksum="94" statRound="90" firstpktOffset="27" lastpktOffset="36" firstpktSeq="7" lastpktSeq="93" />
<RR1 direction="1" statStatus="4" syncStatus="37" statTime="1700390700000" intervalms="900000" duplicatepkts="23" dmin="68" dmean="89" dvpMi="10" dvp95="20" lostperiods="6" jmin="19" dpMi="50" dvmean="15" lostperc="1" lostburstmax="92" jmax="68" dStdDev="8" lostpkts="5" dvpHi="78" dp25="63" toolatepkts="30" lostburstmin="74" dvpLo="41" vpriomin="11" dp95="59" dvmax="79" jmean="71" tosmin="1" jpMi="75" jpLo="84" ttlmin="25" dvp50="72" rxbytes="12" misorderpkts="28" jStdDev="57" jp25="5" jpHi="95" vpriomax="9" dpLo="5" mos="35" ttlmax="4" jp95="53" dvp75="66" jp50="65" dp50="7" jp75="20" rxpkts="53" dvp25="86" dpHi="48" dmax="39" dp75="70" tosmax="98" cksum="70" statRound="32" firstpktOffset="7" lastpktOffset="26" firstpktSeq="55" lastpktSeq="99" />
</RR>
<RR cid="1296003533" sid="533" eod="0">
<RR1 direction="0" statStatus="37" syncStatus="87" statTime="1700390700000" intervalms="900000" duplicatepkts="54" dmin="7" dmean="2" dvpMi="0" dvp95="63" lostperiods="60" jmin="89" dpMi="70" dvmean="54" lostperc="71" lostburstmax="87" jmax="15" dStdDev="65" lostpkts="88" dvpHi="53" dp25="32" toolatepkts="68" lostburstmin="95" dvpLo="39" vpriomin="54" dp95="11" dvmax="6" jmean="63" tosmin="71" jpMi="25" jpLo="50" ttlmin="37" dvp50="3" rxbytes="53" misorderpkts="47" jStdDev="40" jp25="10" jpHi="39" vpriomax="55" dpLo="60" mos="58" ttlmax="45" jp95="25" dvp75="84" jp50="82" dp50="25" jp75="58" rxpkts="13" dvp25="72" dpHi="25" dmax="45" dp75="41" tosmax="23" cksum="99" statRound="26" firstpktOffset="99" lastpktOffset="60" firstpktSeq="39" lastpktSeq="73" />
<RR1 direction="1" statStatus="19" syncStatus="41" statTime="1700390700000" intervalms="900000" duplicatepkts="49" dmin="37" dmean="94" dvpMi="80" dvp95="67" lostperiods="32" jmin="84" dpMi="44" dvmean="53" lostperc="95" lostburstmax="89" jmax="37" dStdDev="2" lostpkts="97" dvpHi="59" dp25="47" toolatepkts="78" lostburstmin="14" dvpLo="10" vpriomin="3" dp95="44" dvmax="10" jmean="86" tosmin="0" jpMi="87" jpLo="48" ttlmin="28" dvp50="40" rxbytes="36" misorderpkts="43" jStdDev="48" jp25="88" jpHi="27" vpriomax="44" dpLo="13" mos="55" ttlmax="67" jp95="59" dvp75="55" jp50="9" dp50="4" jp75="64" rxpkts="12" dvp25="53" dpHi="77" dmax="71" dp75="25" tosmax="39" cksum="33" statRound="3" firstpktOffset="31" lastpktOffset="44" firstpktSeq="80" lastpktSeq="90" />
</RR>
</Response>
</Ptexport>
