<Ptexport version="1.3.0">
<Response>
<RR cid="1296002766" sid="766" eod="0">
<RR1 direction="0" statStatus="73" syncStatus="49" statTime="1700389800000" intervalms="900000" duplicatepkts="52" dmin="45" dmean="6" dvpMi="82" dvp95="28" lostperiods="14" jmin="96" dpMi="89" dvmean="86" lostperc="52" lostburstmax="14" jmax="43" dStdDev="30" lostpkts="41" dvpHi="36" dp25="67" toolatepkts="99" lostburstmin="12" dvpLo="90" vpriomin="4" dp95="37" dvmax="77" jmean="2" tosmin="33" jpMi="75" jpLo="14" ttlmin="71" dvp50="73" rxbytes="57" misorderpkts="86" jStdDev="87" jp25="72" jpHi="33" vpriomax="71" dpLo="92" mos="25" ttlmax="42" jp95="43" dvp75="49" jp50="77" dp50="84" jp75="57" rxpkts="79" dvp25="2" dpHi="54" dmax="80" dp75="44" tosmax="13" cksum="0" statRound="67" firstpktOffset="39" lastpktOffset="35" firstpktSeq="71" lastpktSeq="93" />
<RR1 direction="1" statStatus="56" syncStatus="67" statTime="1700389800000" intervalms="900000" duplicatepkts="24" dmin="44" dmean="61" dvpMi="27" dvp95="51" lostperiods="9" jmin="77" dpMi="56" dvmean="45" lostperc="45" lostburstmax="54" jmax="30" dStdDev="22" lostpkts="48" dvpHi="30" dp25="27" toolatepkts="25" lostburstmin="38" dvpLo="52" vpriomin="29" dp95="59" dvmax="40" jmean="36" tosmin="56" jpMi="57" jpLo="62" ttlmin="85" dvp50="83" rxbytes="88" misorderpkts="80" jStdDev="82" jp25="57" jpHi="82" vpriomax="77" dpLo="97" mos="6" ttlmax="91" jp95="26" dvp75="22" jp50="33" dp50="93" jp75="91" rxpkts="40" dvp25="88" dpHi="36" dmax="75" dp75="23" tosmax="49" cksum="15" statRound="56" firstpktOffset="92" lastpktOffset="81" firstpktSeq="43" lastpktSeq="78" />
</RR>
<RR cid="1296002767" sid="767" eod="0">
<RR1 direction="0" statStatus="56" syncStatus="94" statTime="1700389800000" intervalms="900000" duplicatepkts="29" dmin="45" dmean="80" dvpMi="5" dvp95="57" lostperiods="75" jmin="67" dpMi="76" dvmean="78" lostperc="67" lostburstmax="92" jmax="50" dStdDev="92" lostpkts="55" dvpHi="95" dp25="56" toolatepkts="88" lostburstmin="86" dvpLo="20" vpriomin="73" dp95="70" dvmax="79" jmean="17" tosmin="13" jpMi="69" jpLo="37" ttlmin="66" dvp50="22" rxbytes="62" misorderpkts="23" jStdDev="39" jp25="16" jpHi="97" vpriomax="64" dpLo="94" mos="32" ttlmax="10" jp95="22" dvp75="62" jp50="19" dp50="89" jp75="27" rxpkts="29" dvp25="85" dpHi="95" dmax="26" dp75="87" tosmax="21" cksum="14" statRound="37" firstpktOffset="18" lastpktOffset="7" firstpktSeq="54" lastpktSeq="3" />
<RR1 direction="1" statStatus="51" syncStatus="54" statTime="1700389800000" intervalms="900000" duplicatepkts="10" dmin="36" dmean="8" dvpMi="68" dvp95="95" lostperiods="35" jmin="89" dpMi="87" dvmean="93" lostperc="16" lostburstmax="18" jmax="0" dStdDev="37" lostpkts="9" dvpHi="86" dp25="65" toolatepkts="88" lostburstmin="53" dvpLo="91" vpriomin="35" dp95="84" dvmax="99" jmean="43" tosmin="17" jpMi="13" jpLo="95" ttlmin="66" dvp50="50" rxbytes="13" misorderpkts="72" jStdDev="85" jp25="98" jpHi="84" vpriomax="26" dpLo="9" mos="61" ttlmax="23" jp95="81" dvp75="85" jp50="64" dp50="46" jp75="11" rxpkts="74" dvp25="97" dpHi="95" dmax="27" dp75="66" tosmax="78" cksum="31" statRound="74" firstpktOffset="6" lastpktOffset="55" firstpktSeq="41" lastpktSeq="98" />
</RR>
</Response>
</Ptexport>
