<Ptexport version="1.3.0">
<Response>
<RR cid="1296003386" sid="386" eod="0">
<RR1 direction="0" statStatus="46" syncStatus="79" statTime="1700390700000" intervalms="900000" duplicatepkts="29" dmin="13" dmean="24" dvpMi="35" dvp95="19" lostperiods="2" jmin="45" dpMi="32" dvmean="44" lostperc="60" lostburstmax="42" jmax="37" dStdDev="15" lostpkts="46" dvpHi="59" dp25="80" toolatepkts="24" lostburstmin="37" dvpLo="47" vpriomin="41" dp95="8" dvmax="94" jmean="72" tosmin="16" jpMi="0" jpLo="45" ttlmin="62" dvp50="82" rxbytes="31" misorderpkts="14" jStdDev="59" jp25="55" jpHi="70" vpriomax="53" dpLo="69" mos="85" ttlmax="80" jp95="58" dvp75="48" jp50="4" dp50="18" jp75="17" rxpkts="58" dvp25="34" dpHi="49" dmax="61" dp75="52" tosmax="87" cksum="24" statRound="16" firstpktOffset="15" lastpktOffset="89" firstpktSeq="3" lastpktSeq="0" />
<RR1 direction="1" statStatus="31" syncStatus="11" statTime="1700390700000" intervalms="900000" duplicatepkts="95" dmin="57" dmean="42" dvpMi="46" dvp95="63" lostperiods="18" jmin="34" dpMi="31" dvmean="37" lostperc="28" lostburstmax="40" jmax="20" dStdDev="18" lostpkts="49" dvpHi="5" dp25="73" toolatepkts="56" lostburstmin="85" dvpLo="98" vpriomin="4" dp95="85" dvmax="0" jmean="74" tosmin="1" jpMi="77" jpLo="92" ttlmin="60" dvp50="28" rxbytes="84" misorderpkts="68" jStdDev="57" jp25="51" jpHi="81" vpriomax="75" dpLo="82" mos="21" ttlmax="90" jp95="9" dvp75="37" jp50="59" dp50="33" jp75="45" rxpkts="85" dvp25="53" dpHi="84" dmax="93" dp75="9" tosmax="63" cksum="38" statRound="84" firstpktOffset="62" lastpktOffset="11" firstpktSeq="27" lastpktSeq="89" />
</RR>
<RR cid="1296003387" sid="387" eod="0">
<RR1 direction="0" statStatus="99" syncStatus="52" statTime="1700390700000" intervalms="900000" duplicatepkts="41" dmin="34" dmean="19" dvpMi="33" dvp95="6" lostperiods="79" jmin="88" dpMi="91" dvmean="70" lostperc="16" lostburstmax="32" jmax="2" dStdDev="43" lostpkts="5" dvpHi="19" dp25="50" toolatepkts="87" lostburstmin="56" dvpLo="62" vpriomin="83" dp95="67" dvmax="75" jmean="53" tosmin="10" jpMi="81" jpLo="13" ttlmin="63" dvp50="38" rxbytes="72" misorderpkts="93" jStdDev="98" jp25="30" jpHi="40" vpriomax="38" dpLo="69" mos="78" ttlmax="33" jp95="1" dvp75="48" jp50="90" dp50="73" jp75="87" rxpkts="43" dvp25="11" dpHi="38" dmax="23" dp75="83" tosmax="57" cksum="62" statRound="94" firstpktOffset="27" lastpktOffset="5" firstpktSeq="67" lastpktSeq="66" />
<RR1 direction="1" statStatus="28" syncStatus="24" statTime="1700390700000" intervalms="900000" duplicatepkts="88" dmin="61" dmean="37" dvpMi="84" dvp95="22" lostperiods="26" jmin="74" dpMi="23" dvmean="37" lostperc="15" lostburstmax="72" jmax="16" dStdDev="80" lostpkts="74" dvpHi="2" dp25="26" toolatepkts="99" lostburstmin="65" dvpLo="43" vpriomin="53" dp95="45" dvmax="50" jmean="70" tosmin="69" jpMi="93" jpLo="32" ttlmin="38" dvp50="53" rxbytes="5" misorderpkts="77" jStdDev="49" jp25="61" jpHi="9" vpriomax="41" dpLo="78" mos="84" ttlmax="14" jp95="72" dvp75="15" jp50="77" dp50="32" jp75="16" rxpkts="41" dvp25="77" dpHi="77" dmax="19" dp75="50" tosmax="39" cksum="91" statRound="94" firstpktOffset="40" lastpktOffset="2" firstpktSeq="85" lastpktSeq="33" />
</RR>
</Response>
</Ptexport>
