<Ptexport version="1.3.0">
<Response>
<RR cid="1296001134" sid="134" eod="0">
<RR1 direction="0" statStatus="94" syncStatus="78" statTime="1700388900000" intervalms="900000" duplicatepkts="87" dmin="17" dmean="39" dvpMi="42" dvp95="73" lostperiods="96" jmin="93" dpMi="20" dvmean="54" lostperc="99" lostburstmax="22" jmax="78" dStdDev="29" lostpkts="84" dvpHi="63" dp25="79" toolatepkts="94" lostburstmin="21" dvpLo="68" vpriomin="60" dp95="76" dvmax="91" jmean="7" tosmin="62" jpMi="66" jpLo="64" ttlmin="92" dvp50="5" rxbytes="40" misorderpkts="36" jStdDev="81" jp25="37" jpHi="11" vpriomax="83" dpLo="72" mos="47" ttlmax="98" jp95="71" dvp75="47" jp50="13" dp50="13" jp75="40" rxpkts="89" dvp25="44" dpHi="32" dmax="19" dp75="55" tosmax="79" cksum="65" statRound="39" firstpktOffset="57" lastpktOffset="53" firstpktSeq="30" lastpktSeq="45" />
<RR1 direction="1" statStatus="91" syncStatus="20" statTime="1700388900000" intervalms="900000" duplicatepkts="40" dmin="7" dmean="39" dvpMi="71" dvp95="87" lostperiods="53" jmin="54" dpMi="45" dvmean="8" lostperc="79" lostburstmax="54" jmax="23" dStdDev="36" lostpkts="68" dvpHi="52" dp25="0" toolatepkts="79" lostburstmin="0" dvpLo="56" vpriomin="38" dp95="17" dvmax="35" jmean="18" tosmin="46" jpMi="51" jpLo="52" ttlmin="32" dvp50="63" rxbytes="66" misorderpkts="38" jStdDev="91" jp25="21" jpHi="92" vpriomax="64" dpLo="26" mos="84" ttlmax="68" jp95="34" dvp75="22" jp50="28" dp50="83" jp75="54" rxpkts="23" dvp25="66" dpHi="17" dmax="44" dp75="87" tosmax="7" cksum="15" statRound="30" firstpktOffset="26" lastpktOffset="35" firstpktSeq="86" lastpktSeq="51" />
</RR>
<RR cid="1296001135" sid="135" eod="0">
<RR1 direction="0" statStatus="28" syncStatus="85" statTime="1700388900000" intervalms="900000" duplicatepkts="1" dmin="39" dmean="5" dvpMi="47" dvp95="76" lostperiods="0" jmin="39" dpMi="19" dvmean="51" lostperc="36" lostburstmax="30" jmax="40" dStdDev="12" lostpkts="93" dvpHi="88" dp25="66" toolatepkts="29" lostburstmin="20" dvpLo="88" vpriomin="44" dp95="10" dvmax="27" jmean="31" tosmin="54" jpMi="72" jpLo="58" ttlmin="50" dvp50="98" rxbytes="23" misorderpkts="21" jStdDev="46" jp25="33" jpHi="61" vpriomax="91" dpLo="62" mos="23" ttlmax="40" jp95="26" dvp75="23" jp50="26" dp50="63" jp75="94" rxpkts="48" dvp25="11" dpHi="1" dmax="14" dp75="70" tosmax="20" cksum="79" statRound="34" firstpktOffset="56" lastpktOffset="56" firstpktSeq="53" lastpktSeq="92" />
<RR1 direction="1" statStatus="11" syncStatus="60" statTime="1700388900000" intervalms="900000" duplicatepkts="79" dmin="52" dmean="98" dvpMi="33" dvp95="57" lostperiods="92" jmin="3" dpMi="37" dvmean="0" lostperc="56" lostburstmax="50" jmax="96" dStdDev="13" lostpkts="20" dvpHi="3" dp25="76" toolatepkts="45" lostburstmin="0" dvpLo="20" vpriomin="51" dp95="81" dvmax="72" jmean="38" tosmin="79" jpMi="0" jpLo="2" ttlmin="97" dvp50="27" rxbytes="1" misorderpkts="57" jStdDev="76" jp25="75" jpHi="63" vpriomax="8" dpLo="47" mos="53" ttlmax="44" jp95="76" dvp75="3" jp50="73" dp50="61" jp75="7" rxpkts="4" dvp25="13" dpHi="48" dmax="45" dp75="43" tosmax="22" cksum="70" statRound="62" firstpktOffset="84" lastpktOffset="32" firstpktSeq="20" lastpktSeq="70" />
</RR>
</Response>
</Ptexport>
