<Ptexport version="1.3.0">
<Response>
<RR cid="1296003312" sid="312" eod="0">
<RR1 direction="0" statStatus="47" syncStatus="21" statTime="1700390700000" intervalms="900000" duplicatepkts="12" dmin="29" dmean="55" dvpMi="58" dvp95="34" lostperiods="51" jmin="98" dpMi="34" dvmean="12" lostperc="53" lostburstmax="26" jmax="92" dStdDev="65" lostpkts="80" dvpHi="71" dp25="96" toolatepkts="8" lostburstmin="60" dvpLo="31" vpriomin="71" dp95="3" dvmax="30" jmean="24" tosmin="52" jpMi="65" jpLo="73" ttlmin="28" dvp50="91" rxbytes="30" misorderpkts="16" jStdDev="50" jp25="29" jpHi="40" vpriomax="75" dpLo="72" mos="48" ttlmax="89" jp95="26" dvp75="36" jp50="86" dp50="14" jp75="9" rxpkts="0" dvp25="51" dpHi="85" dmax="90" dp75="4" tosmax="76" cksum="57" statRound="96" firstpktOffset="24" lastpktOffset="17" firstpktSeq="20" lastpktSeq="59" />
<RR1 direction="1" statStatus="99" syncStatus="50" statTime="1700390700000" intervalms="900000" duplicatepkts="48" dmin="32" dmean="20" dvpMi="29" dvp95="29" lostperiods="9" jmin="63" dpMi="17" dvmean="82" lostperc="21" lostburstmax="41" jmax="57" dStdDev="31" lostpkts="86" dvpHi="1" dp25="49" toolatepkts="41" lostburstmin="56" dvpLo="4" vpriomin="56" dp95="17" dvmax="66" jmean="26" tosmin="4" jpMi="21" jpLo="50" ttlmin="17" dvp50="24" rxbytes="38" misorderpkts="4" jStdDev="49" jp25="90" jpHi="23" vpriomax="78" dpLo="59" mos="58" ttlmax="67" jp95="83" dvp75="52" jp50="5" dp50="60" jp75="92" rxpkts="21" dvp25="38" dpHi="43" dmax="93" dp75="36" tosmax="23" cksum="49" statRound="11" firstpktOffset="68" lastpktOffset="63" firstpktSeq="30" lastpktSeq="11" />
</RR>
<RR cid="1296003313" sid="313" eod="0">
<RR1 direction="0" statStatus="65" syncStatus="3" statTime="1700390700000" intervalms="900000" duplicatepkts="70" dmin="0" dmean="95" dvpMi="71" dvp95="36" lostperiods="44" jmin="27" dpMi="55" dvmean="23" lostperc="86" lostburstmax="62" jmax="50" dStdDev="84" lostpkts="60" dvpHi="89" dp25="82" toolatepkts="9" lostburstmin="90" dvpLo="59" vpriomin="12" dp95="34" dvmax="38" jmean="18" tosmin="81" jpMi="25" jpLo="51" ttlmin="18" dvp50="80" rxbytes="82" misorderpkts="84" jStdDev="88" jp25="75" jpHi="37" vpriomax="88" dpLo="73" mos="29" ttlmax="6" jp95="14" dvp75="12" jp50="2" dp50="83" jp75="23" rxpkts="47" dvp25="59" dpHi="18" dmax="92" dp75="48" tosmax="1" cksum="13" statRound="54" firstpktOffset="4" lastpktOffset="3" firstpktSeq="44" lastpktSeq="79" />
<RR1 direction="1" statStatus="74" syncStatus="51" statTime="1700390700000" intervalms="900000" duplicatepkts="59" dmin="55" dmean="10" dvpMi="97" dvp95="59" lostperiods="26" jmin="53" dpMi="58" dvmean="20" lostperc="44" lostburstmax="63" jmax="66" dStdDev="19" lostpkts="15" dvpHi="96" dp25="6" toolatepkts="73" lostburstmin="46" dvpLo="24" vpriomin="96" dp95="92" dvmax="50" jmean="15" tosmin="8" jpMi="65" jpLo="40" ttlmin="34" dvp50="4" rxbytes="74" misorderpkts="20" jStdDev="38" jp25="20" jpHi="39" vpriomax="66" dpLo="94" mos="26" ttlmax="31" jp95="16" dvp75="90" jp50="16" dp50="5" jp75="26" rxpkts="73" dvp25="72" dpHi="15" dmax="52" dp75="94" tosmax="25" cksum="50" statRound="28" firstpktOffset="32" lastpktOffset="40" firstpktSeq="43" lastpktSeq="40" />
</RR>
</Response>
</Ptexport>
