<Ptexport version="1.3.0">
<Response>
<RR cid="1296003260" sid="260" eod="0">
<RR1 direction="0" statStatus="32" syncStatus="73" statTime="1700390700000" intervalms="900000" duplicatepkts="51" dmin="41" dmean="45" dvpMi="52" dvp95="76" lostperiods="56" jmin="35" dpMi="20" dvmean="72" lostperc="17" lostburstmax="2" jmax="44" dStdDev="52" lostpkts="54" dvpHi="10" dp25="97" toolatepkts="46" lostburstmin="37" dvpLo="18" vpriomin="20" dp95="91" dvmax="86" jmean="94" tosmin="35" jpMi="93" jpLo="70" ttlmin="19" dvp50="61" rxbytes="49" misorderpkts="12" jStdDev="25" jp25="37" jpHi="8" vpriomax="79" dpLo="93" mos="69" ttlmax="29" jp95="84" dvp75="56" jp50="0" dp50="43" jp75="22" rxpkts="47" dvp25="16" dpHi="58" dmax="3" dp75="4" tosmax="45" cksum="31" statRound="5" firstpktOffset="4" lastpktOffset="61" firstpktSeq="2" lastpktSeq="29" />
<RR1 direction="1" statStatus="4" syncStatus="37" statTime="1700390700000" intervalms="900000" duplicatepkts="61" dmin="35" dmean="60" dvpMi="7" dvp95="89" lostperiods="22" jmin="99" dpMi="72" dvmean="46" lostperc="44" lostburstmax="11" jmax="94" dStdDev="44" lostpkts="72" dvpHi="70" dp25="64" toolatepkts="57" lostburstmin="81" dvpLo="13" vpriomin="57" dp95="68" dvmax="61" jmean="10" tosmin="40" jpMi="19" jpLo="92" ttlmin="35" dvp50="8" rxbytes="22" misorderpkts="43" jStdDev="86" jp25="47" jpHi="68" vpriomax="31" dpLo="12" mos="8" ttlmax="82" jp95="54" dvp75="41" jp50="16" dp50="36" jp75="76" rxpkts="18" dvp25="41" dpHi="87" dmax="87" dp75="25" tosmax="54" cksum="14" statRound="46" firstpktOffset="12" lastpktOffset="9" firstpktSeq="95" lastpktSeq="78" />
</RR>
<RR cid="1296003261" sid="261" eod="0">
<RR1 direction="0" statStatus="71" syncStatus="30" statTime="1700390700000" intervalms="900000" duplicatepkts="98" dmin="36" dmean="27" dvpMi="5" dvp95="12" lostperiods="4" jmin="46" dpMi="2" dvmean="18" lostperc="22" lostburstmax="2" jmax="39" dStdDev="71" lostpkts="83" dvpHi="47" dp25="96" toolatepkts="13" lostburstmin="96" dvpLo="79" vpriomin="18" dp95="66" dvmax="24" jmean="15" tosmin="17" jpMi="11" jpLo="44" ttlmin="20" dvp50="11" rxbytes="67" misorderpkts="79" jStdDev="94" jp25="81" jpHi="97" vpriomax="65" dpLo="9" mos="46" ttlmax="84" jp95="77" dvp75="54" jp50="72" dp50="7" jp75="95" rxpkts="50" dvp25="18" dpHi="39" dmax="52" dp75="59" tosmax="74" cksum="65" statRound="8" firstpktOffset="64" lastpktOffset="13" firstpktSeq="75" lastpktSeq="5" />
<RR1 direction="1" statStatus="49" syncStatus="42" statTime="1700390700000" intervalms="900000" duplicatepkts="63" dmin="65" dmean="61" dvpMi="66" dvp95="10" lostperiods="38" jmin="54" dpMi="96" dvmean="40" lostperc="64" lostburstmax="38" jmax="18" dStdDev="13" lostpkts="70" dvpHi="84" dp25="49" toolatepkts="6" lostburstmin="18" dvpLo="16" vpriomin="37" dp95="57" dvmax="19" jmean="41" tosmin="23" jpMi="44" jpLo="29" ttlmin="30" dvp50="12" rxbytes="78" misorderpkts="99" jStdDev="51" jp25="8" jpHi="49" vpriomax="69" dpLo="27" mos="44" ttlmax="57" jp95="85" dvp75="22" jp50="45" dp50="15" jp75="75" rxpkts="47" dvp25="89" dpHi="78" dmax="26" dp75="69" tosmax="69" cksum="68" statRound="8" firstpktOffset="80" lastpktOffset="21" firstpktSeq="53" lastpktSeq="18" />
</RR>
</Response>
</Ptexport>
