<Ptexport version="1.3.0">
<Response>
<RR cid="1296001068" sid="68" eod="0">
<RR1 direction="0" statStatus="72" syncStatus="48" statTime="1700388900000" intervalms="900000" duplicatepkts="39" dmin="56" dmean="78" dvpMi="24" dvp95="61" lostperiods="29" jmin="90" dpMi="45" dvmean="96" lostperc="81" lostburstmax="82" jmax="86" dStdDev="40" lostpkts="82" dvpHi="71" dp25="6" toolatepkts="45" lostburstmin="69" dvpLo="67" vpriomin="1" dp95="73" dvmax="11" jmean="25" tosmin="89" jpMi="36" jpLo="14" ttlmin="8" dvp50="80" rxbytes="99" misorderpkts="65" jStdDev="66" jp25="13" jpHi="19" vpriomax="1" dpLo="61" mos="55" ttlmax="25" jp95="80" dvp75="42" jp50="30" dp50="67" jp75="81" rxpkts="14" dvp25="9" dpHi="23" dmax="58" dp75="63" tosmax="52" cksum="89" statRound="74" firstpktOffset="41" lastpktOffset="32" firstpktSeq="17" lastpktSeq="51" />
<RR1 direction="1" statStatus="97" syncStatus="47" statTime="1700388900000" intervalms="900000" duplicatepkts="61" dmin="30" dmean="89" dvpMi="71" dvp95="44" lostperiods="45" jmin="61" dpMi="51" dvmean="14" lostperc="25" lostburstmax="85" jmax="88" dStdDev="92" lostpkts="88" dvpHi="23" dp25="52" toolatepkts="58" lostburstmin="87" dvpLo="48" vpriomin="44" dp95="45" dvmax="19" jmean="3" tosmin="38" jpMi="10" jpLo="69" ttlmin="45" dvp50="64" rxbytes="85" misorderpkts="79" jStdDev="25" jp25="22" jpHi="68" vpriomax="23" dpLo="26" mos="65" ttlmax="44" jp95="6" dvp75="71" jp50="92" dp50="62" jp75="34" rxpkts="27" dvp25="32" dpHi="97" dmax="65" dp75="37" tosmax="37" cksum="52" statRound="25" firstpktOffset="14" lastpktOffset="98" firstpktSeq="34" lastpktSeq="50" />
</RR>
<RR cid="1296001069" sid="69" eod="0">
<RR1 direction="0" statStatus="79" syncStatus="48" statTime="1700388900000" intervalms="900000" duplicatepkts="60" dmin="34" dmean="35" dvpMi="46" dvp95="68" lostperiods="55" jmin="12" dpMi="7" dvmean="70" lostperc="28" lostburstmax="70" jmax="37" dStdDev="45" lostpkts="21" dvpHi="5" dp25="96" toolatepkts="12" lostburstmin="14" dvpLo="20" vpriomin="55" dp95="85" dvmax="83" jmean="66" tosmin="10" jpMi="27" jpLo="45" ttlmin="66" dvp50="92" rxbytes="60" misorderpkts="88" jStdDev="28" jp25="31" jpHi="82" vpriomax="38" dpLo="87" mos="35" ttlmax="79" jp95="59" dvp75="62" jp50="16" dp50="68" jp75="59" rxpkts="22" dvp25="20" dpHi="56" dmax="11" dp75="4" tosmax="2" cksum="12" statRound="38" firstpktOffset="12" lastpktOffset="70" firstpktSeq="65" lastpktSeq="65" />
<RR1 direction="1" statStatus="46" syncStatus="24" statTime="1700388900000" intervalms="900000" duplicatepkts="80" dmin="13" dmean="66" dvpMi="30" dvp95="8" lostperiods="0" jmin="40" dpMi="9" dvmean="59" lostperc="15" lostburstmax="18" jmax="56" dStdDev="67" lostpkts="42" dvpHi="17" dp25="81" toolatepkts="38" lostburstmin="61" dvpLo="86" vpriomin="37" dp95="97" dvmax="91" jmean="13" tosmin="0" jpMi="23" jpLo="0" ttlmin="51" dvp50="55" rxbytes="86" misorderpkts="16" jStdDev="62" jp25="17" jpHi="65" vpriomax="22" dpLo="3" mos="94" ttlmax="97" jp95="88" dvp75="87" jp50="15" dp50="88" jp75="57" rxpkts="29" dvp25="74" dpHi="57" dmax="20" dp75="13" tosmax="65" cksum="32" statRound="87" firstpktOffset="43" lastpktOffset="63" firstpktSeq="67" lastpktSeq="30" />
</RR>
</Response>
</Ptexport>
