<?xml version="1.0" encoding="UTF-8"?>
<?xml-stylesheet type="text/xsl" href="MeasDataCollection.xsl"?>
<!DOCTYPE mdc SYSTEM "MeasDataCollection.dtd">
<mdc xmlns:HTML="http://www.w3.org/TR/REC-xml">
<mfh>
<ffv>32.401 V5.0</ffv>
<sn>DC=ipworks.com,g3SubNetwork=US,Node_Distinguished_Name=IPWk03</sn>
<st>IPWORKS</st>
<vn>Ericsson</vn>
<cbt>20231105100000+0200</cbt>
</mfh>
<md>
<neid>
<neun></neun>
<nedn>DC=ipworks.com,g3SubNetwork=US,Node_Distinguished_Name=IPWk03</nedn>
</neid>
<mi>
<mts>20231105101500+0200</mts>
<gp>900</gp>
<mt>Load-1</mt>
<mt>Load-15</mt>
<mt>Load-15 (laLoad)</mt>
<mt>Load-1 (laLoad)</mt>
<mt>Load-5</mt>
<mt>Load-5 (laLoad)</mt>
<mt>dskAvail</mt>
<mt>dskTotal</mt>
<mt>dskUsed</mt>
<mt>ifInDiscards</mt>
<mt>ifInErrors</mt>
<mt>ifInOctets</mt>
<mt>ifInUcastPkts</mt>
<mt>ifInUnknownProtos</mt>
<mt>ifOutDiscards</mt>
<mt>ifOutErrors</mt>
<mt>ifOutOctets</mt>
<mt>ifOutUcastPkts</mt>
<mt>memAvailReal</mt>
<mt>memAvailSwap</mt>
<mt>memTotalFree</mt>
<mt>memTotalReal</mt>
<mt>memTotalSwap</mt>
<mt>ssCpuRawIdle</mt>
<mt>ssCpuRawSystem</mt>
<mt>ssCpuRawUser</mt>
<mv>
<moid>PLATFORM=DEFAULT,Source = Processor1</moid>
<r>7</r>
<r>49</r>
<r>20</r>
<r>67</r>
<r>82</r>
<r>58</r>
<r>66</r>
<r>16</r>
<r>17</r>
<r>57</r>
<r>25</r>
<r>91</r>
<r>51</r>
<r>16</r>
<r>50</r>
<r>74</r>
<r>31</r>
<r>32</r>
<r>2</r>
<r>15</r>
<r>29</r>
<r>7</r>
<r>88</r>
<r>14</r>
<r>42</r>
<r>32</r>
</mv>
</mi>
</md>
<mff>
<ts>20231105101500+0200</ts>
</mff>
</mdc>