<?xml version="1.0" encoding="UTF-8" standalone="yes"?>
<measCollecFile>
    <fileHeader fileFormatVersion="3GPP_PM_32.435_XML_v7.2.0">
       <fileSender/>
       <measCollec beginTime="2023-11-05T10:00:00+0200"/>
    </fileHeader>
    <measData>
        <managedElement/>
        <measInfo>
        <job jobId="RSASUBS39job"/>
         <granPeriod duration="PT900S" endTime="2023-11-05T10:15:00+0200"/>
         <repPeriod duration="PT900S"/>
         <measType p="0">NSUBSRSA1.actual</measType>
         <measType p="1">NSUBSRSA2.actual</measType>
         <measType p="2">NSUBSRSA3.actual</measType>
         <measType p="3">NSUBSRSA4.actual</measType>
         <measType p="4">NSUBSRSA5.actual</measType>
         <measType p="5">NSUBSRSA6.actual</measType>
         <measType p="6">NSUBSRSA7.actual</measType>
         <measType p="7">NSUBSRSA8.actual</measType>
         <measType p="8">NSUBSRSA9.actual</measType>
         <measType p="9">NSUBSRSA10.actual</measType>
         <measType p="10">NSUBSRSA11.actual</measType>
         <measType p="11">NSUBSRSA12.actual</measType>
         <measType p="12">NSUBSRSA13.actual</measType>
         <measType p="13">NSUBSRSA14.actual</measType>
         <measType p="14">NSUBSRSA15.actual</measType>
         <measType p="15">NSUBSRSA16.actual</measType>
         <measType p="16">NSUBSRSA17.actual</measType>
         <measType p="17">NSUBSRSA18.actual</measType>
         <measType p="18">NSUBSRSA19.actual</measType>
         <measType p="19">NSUBSRSA20.actual</measType>
         <measType p="20">NSUBSRSA21.actual</measType>
         <measType p="21">NSUBSRSA22.actual</measType>
         <measType p="22">NSUBSRSA23.actual</measType>
         <measType p="23">NSUBSRSA24.actual</measType>
         <measType p="24">NSUBSRSA25.actual</measType>
         <measType p="25">NSUBSRSA26.actual</measType>
         <measType p="26">NSUBSRSA27.actual</measType>
         <measType p="27">NSUBSRSA28.actual</measType>
         <measType p="28">NSUBSRSA29.actual</measType>
         <measType p="29">NSUBSRSA30.actual</measType>
         <measType p="30">NSUBSRSA31.actual</measType>
         <measType p="31">NSUBSRSA32.actual</measType>
         <measType p="32">NSUBSRSA33.actual</measType>
         <measType p="33">NSUBSRSA34.actual</measType>
         <measType p="34">NSUBSRSA35.actual</measType>
         <measType p="35">NSUBSRSA36.actual</measType>
         <measType p="36">NSUBSRSA37.actual</measType>
         <measType p="37">NSUBSRSA38.actual</measType>
         <measType p="38">NSUBSRSA39.actual</measType>
         <measType p="39">NSUBSRSA40.actual</measType>
         <measType p="40">NSUBSRSA41.actual</measType>
         <measType p="41">NSUBSRSA42.actual</measType>
         <measType p="42">NSUBSRSA43.actual</measType>
         <measType p="43">NSUBSRSA44.actual</measType>
         <measType p="44">NSUBSRSA45.actual</measType>
         <measType p="45">NSUBSRSA46.actual</measType>
         <measType p="46">NSUBSRSA47.actual</measType>
         <measType p="47">NSUBSRSA48.actual</measType>
         <measType p="48">NSUBSRSA49.actual</measType>
         <measType p="49">NSUBSRSA50.actual</measType>
         <measType p="50">NSUBSRSA51.actual</measType>
         <measType p="51">NSUBSRSA52.actual</measType>
         <measType p="52">NSUBSRSA53.actual</measType>
         <measType p="53">NSUBSRSA54.actual</measType>
         <measType p="54">NSUBSRSA55.actual</measType>
         <measType p="55">NSUBSRSA56.actual</measType>
         <measType p="56">NSUBSRSA57.actual</measType>
         <measType p="57">NSUBSRSA58.actual</measType>
         <measType p="58">NSUBSRSA59.actual</measType>
         <measType p="59">NSUBSRSA60.actual</measType>
         <measType p="60">NSUBSRSA61.actual</measType>
         <measType p="61">NSUBSRSA62.actual</measType>
         <measType p="62">NSUBSRSA63.actual</measType>
         <measType p="63">NSUBSRSA64.actual</measType>
		 <measValue measObjLdn="CUDBSYS=1,SUBSCR_ID=1">
             <r p="0">5735841</r>
             <r p="1">5737175</r>
             <r p="2">5823586</r>
             <r p="3">5743074</r>
             <r p="4">5777210</r>
             <r p="5">5791560</r>
             <r p="6">5769096</r>
             <r p="7">5849722</r>
             <r p="8">5773255</r>
             <r p="9">5830105</r>
             <r p="10">5794634</r>
             <r p="11">5783394</r>
             <r p="12">5737856</r>
             <r p="13">5822263</r>
             <r p="14">5837097</r>
             <r p="15">5831775</r>
             <r p="16">5842140</r>
             <r p="17">5828647</r>
             <r p="18">5731341</r>
             <r p="19">5832637</r>
             <r p="20">5746741</r>
             <r p="21">5745376</r>
             <r p="22">5786646</r>
             <r p="23">5836092</r>
             <r p="24">5766743</r>
             <r p="25">5755985</r>
             <r p="26">5736938</r>
             <r p="27">5817456</r>
             <r p="28">5849396</r>
             <r p="29">5738612</r>
             <r p="30">5821699</r>
             <r p="31">5739698</r>
             <r p="32">5792668</r>
             <r p="33">5741391</r>
             <r p="34">5792377</r>
             <r p="35">5766864</r>
             <r p="36">5770822</r>
             <r p="37">5732848</r>
             <r p="38">5823907</r>
             <r p="39">5753247</r>
             <r p="40">5738311</r>
             <r p="41">5825659</r>
             <r p="42">5733276</r>
             <r p="43">5752382</r>
             <r p="44">5766295</r>
             <r p="45">5814928</r>
             <r p="46">5842683</r>
             <r p="47">5801974</r>
             <r p="48">5784694</r>
             <r p="49">5796755</r>
             <r p="50">5822790</r>
             <r p="51">5831173</r>
             <r p="52">5763655</r>
             <r p="53">5742090</r>
             <r p="54">5828545</r>
             <r p="55">5802573</r>
             <r p="56">5834281</r>
             <r p="57">5792035</r>
             <r p="58">5771661</r>
             <r p="59">5756399</r>
             <r p="60">5734083</r>
             <r p="61">5807988</r>
             <r p="62">5835439</r>
             <r p="63">5796038</r>
         </measValue>
        </measInfo>
    </measData>
    <fileFooter>
       <measCollec endTime="2023-11-05T10:15:00+0200"/>
    </fileFooter>
</measCollecFile>
